haigen/__init__.py
haigen/main.py
haigen-0.5.2.dist-info/METADATA
haigen-0.5.2.dist-info/WHEEL
haigen-0.5.2.dist-info/top_level.txt
haigen-0.5.2.dist-info/RECORD
